{
	"name": "DEX_LOCATION_DELTA",
	"properties": {
		"activities": [
			{
				"name": "Copy data1",
				"type": "Copy",
				"dependsOn": [],
				"policy": {
					"timeout": "0.12:00:00",
					"retry": 0,
					"retryIntervalInSeconds": 30,
					"secureOutput": false,
					"secureInput": false
				},
				"userProperties": [],
				"typeProperties": {
					"source": {
						"type": "OracleSource",
						"oracleReaderQuery": "select LOC.*, case when NVL(last_update_tstmp, '01-JAN-1980') > NVL(last_run_tstmp, '01-JAN-1980') then last_update_tstmp else last_run_tstmp end as GREATEST_UPDATE_TSTMP\r\nfrom MIRDBP.STO_LOCATION LOC\r\nwhere case when NVL(last_update_tstmp, '01-JAN-1980') > NVL(last_run_tstmp, '01-JAN-1980') then last_update_tstmp else last_run_tstmp end > (CURRENT_TIMESTAMP - 26/24 - 1/24)",
						"partitionOption": "None",
						"queryTimeout": "02:00:00"
					},
					"sink": {
						"type": "AzureSqlSink",
						"writeBehavior": "upsert",
						"upsertSettings": {
							"useTempDB": true,
							"keys": [
								"SEQUENCE_NUM"
							]
						},
						"sqlWriterUseTableLock": false,
						"disableMetricsCollection": false
					},
					"enableStaging": false,
					"translator": {
						"type": "TabularTranslator",
						"typeConversion": true,
						"typeConversionSettings": {
							"allowDataTruncation": true,
							"treatBooleanAsNumber": false
						}
					}
				},
				"inputs": [
					{
						"referenceName": "DEX_STO_LOCATION",
						"type": "DatasetReference"
					}
				],
				"outputs": [
					{
						"referenceName": "az_sql_tbl_LOCATION",
						"type": "DatasetReference"
					}
				]
			}
		],
		"folder": {
			"name": "DEX!!!DO_NOT_RUN_WONADWH_PRE_1PM!!!"
		},
		"annotations": []
	}
}